Metadata-Version: 2.1
Name: spacememo
Version: 0.1.6
Summary: 📘 a python nanolibrary for apply “spaced repetition” in learning purposes apps 📙
Home-page: https://github.com/opensourceducation/spacememo
Author: opensourceducation
Author-email: githubpersonalfor@gmail.com
License: MIT license
Keywords: srs,learning,microlearning,memorization,javascript,space-repetition,python
Classifier: Programming Language :: Python :: 3
Classifier: Intended Audience :: Education
Classifier: License :: OSI Approved :: MIT License
Classifier: Operating System :: OS Independent
Requires-Python: >=3.6
